vrot/.DS_Store
vrot/__init__.py
vrot/middleware.py
vrot/static/.DS_Store
vrot/static/vrot/timezone.js
vrot/templatetags/.DS_Store
vrot/templatetags/__init__.py
vrot/templatetags/vrot.py
django_vrot-0.3.0.dist-info/licenses/LICENSE
django_vrot-0.3.0.dist-info/WHEEL
django_vrot-0.3.0.dist-info/METADATA
django_vrot-0.3.0.dist-info/RECORD
