Metadata-Version: 2.4
Name: django-vrot
Version: 0.3.0
Summary: A collection of Django templatetags and middleware.
Keywords: django,templatetags,middleware,timezone,localization,template,filters,humanize,active-link,query-params
Author: Kevin Renskers
Author-email: Kevin Renskers <kevin@loopwerk.io>
License-Expression: MIT
License-File: LICENSE
Classifier: Development Status :: 4 - Beta
Classifier: Environment :: Web Environment
Classifier: Framework :: Django
Classifier: Framework :: Django :: 3.2
Classifier: Framework :: Django :: 4.0
Classifier: Framework :: Django :: 4.1
Classifier: Framework :: Django :: 4.2
Classifier: Framework :: Django :: 5.0
Classifier: Framework :: Django :: 5.1
Classifier: Framework :: Django :: 5.2
Classifier: Intended Audience :: Developers
Classifier: License :: OSI Approved :: MIT License
Classifier: Operating System :: OS Independent
Classifier: Programming Language :: Python
Classifier: Programming Language :: Python :: 3
Classifier: Programming Language :: Python :: 3.9
Classifier: Programming Language :: Python :: 3.10
Classifier: Programming Language :: Python :: 3.11
Classifier: Programming Language :: Python :: 3.12
Classifier: Programming Language :: Python :: 3.13
Classifier: Programming Language :: JavaScript
Classifier: Topic :: Internet :: WWW/HTTP
Classifier: Topic :: Internet :: WWW/HTTP :: Dynamic Content
Classifier: Topic :: Software Development :: Libraries :: Python Modules
Requires-Dist: django>=3.2.0
Requires-Python: >=3.9
Project-URL: Homepage, https://github.com/loopwerk/django-vrot/
Project-URL: Issues, https://github.com/loopwerk/django-vrot/issues
Project-URL: Repository, https://github.com/loopwerk/django-vrot.git
